README.rst
setup.py
bin/__init__.py
bin/kdniao
kdniao/__init__.py
kdniao/api.py
kdniao/client.py
kdniao/client_aio.py
kdniao/conf.py
kdniao/mdutils.py
kdniao.egg-info/PKG-INFO
kdniao.egg-info/SOURCES.txt
kdniao.egg-info/dependency_links.txt
kdniao.egg-info/requires.txt
kdniao.egg-info/top_level.txt
test/test_client.py
test/test_recognise.py
test/test_track.py
test/test_users.py